<?xml version="1.0" encoding="utf-8"?>
<LanguageData>

  <CookMisosiru.label>Cook Miso soup x4</CookMisosiru.label>
  <CookMisosiru.description>Dissolve Miso in boiling water and add your favorite ingredients.</CookMisosiru.description>
  <CookMisosiru.jobString>Cooking Miso soup.</CookMisosiru.jobString>

  <CookSoyMilkShake.label>Cook Soy milkshake x4</CookSoyMilkShake.label>
  <CookSoyMilkShake.description>A plain, ordinary milkshake-only it's made with Soy milk and not that other stuff.</CookSoyMilkShake.description>
  <CookSoyMilkShake.jobString>Cooking Soy milkshake.</CookSoyMilkShake.jobString>


</LanguageData>