<?xml version="1.0" encoding="utf-8"?>
<LanguageData>

  <!-- MealFine -->

  <CookASUCroquetteBread.label>コロッケぱんx6</CookASUCroquetteBread.label>
  <CookASUCroquetteBread.description>コロッケぱんを作る</CookASUCroquetteBread.description>
  <CookASUCroquetteBread.jobString>コロッケぱんを作成中。</CookASUCroquetteBread.jobString>

  <CookASUFriedNoodleSandwich.label>焼きそばぱんx6</CookASUFriedNoodleSandwich.label>
  <CookASUFriedNoodleSandwich.description>焼きそばぱんを作る</CookASUFriedNoodleSandwich.description>
  <CookASUFriedNoodleSandwich.jobString>焼きそばぱんを作成中。</CookASUFriedNoodleSandwich.jobString>

  <CookASUSweetBeanPasteBun.label>あんぱんx6</CookASUSweetBeanPasteBun.label>
  <CookASUSweetBeanPasteBun.description>あんぱんを作る</CookASUSweetBeanPasteBun.description>
  <CookASUSweetBeanPasteBun.jobString>あんぱんを作成中。</CookASUSweetBeanPasteBun.jobString>

  <CookASUCreamBun.label>クリームぱんx6</CookASUCreamBun.label>
  <CookASUCreamBun.description>ミルク(豆乳)と卵でクリームを調理後にクリームぱんを作る。</CookASUCreamBun.description>
  <CookASUCreamBun.jobString>クリームぱんを作成中。</CookASUCreamBun.jobString>

  <CookASUChocolateCorne.label>チョココロネx6</CookASUChocolateCorne.label>
  <CookASUChocolateCorne.description>チョココロネを作る</CookASUChocolateCorne.description>
  <CookASUChocolateCorne.jobString>チョココロネを作成中。</CookASUChocolateCorne.jobString>

  <CookASUMelonpan.label>メロンパンx6</CookASUMelonpan.label>
  <CookASUMelonpan.description>メロンパンを作る</CookASUMelonpan.description>
  <CookASUMelonpan.jobString>メロンパンを作成中。</CookASUMelonpan.jobString>

  <CookASUCurryBun.label>カレーパンx6</CookASUCurryBun.label>
  <CookASUCurryBun.description>カレーパンを作る</CookASUCurryBun.description>
  <CookASUCurryBun.jobString>カレーパンを作成中。</CookASUCurryBun.jobString>


</LanguageData>